[{"__symbolic":"module","version":3,"metadata":{"Clipboard":{"__symbolic":"reference","module":"clipboard"},"ClipboardDirective":{"__symbolic":"class","decorators":[{"__symbolic":"call","expression":{"__symbolic":"reference","module":"@angular/core","name":"Directive"},"arguments":[{"selector":"[xngClipboard]"}]}],"members":{"targetElm":[{"__symbolic":"property","decorators":[{"__symbolic":"call","expression":{"__symbolic":"reference","module":"@angular/core","name":"Input"},"arguments":["xngClipboard"]}]}],"cbContent":[{"__symbolic":"property","decorators":[{"__symbolic":"call","expression":{"__symbolic":"reference","module":"@angular/core","name":"Input"}}]}],"onSuccess":[{"__symbolic":"property","decorators":[{"__symbolic":"call","expression":{"__symbolic":"reference","module":"@angular/core","name":"Output"},"arguments":["cbOnSuccess"]}]}],"onError":[{"__symbolic":"property","decorators":[{"__symbolic":"call","expression":{"__symbolic":"reference","module":"@angular/core","name":"Output"},"arguments":["cbOnError"]}]}],"__ctor__":[{"__symbolic":"constructor","parameters":[{"__symbolic":"reference","module":"@angular/core","name":"ElementRef"}]}],"ngOnInit":[{"__symbolic":"method"}],"ngOnDestroy":[{"__symbolic":"method"}]}}}},{"__symbolic":"module","version":1,"metadata":{"Clipboard":{"__symbolic":"reference","module":"clipboard"},"ClipboardDirective":{"__symbolic":"class","decorators":[{"__symbolic":"call","expression":{"__symbolic":"reference","module":"@angular/core","name":"Directive"},"arguments":[{"selector":"[xngClipboard]"}]}],"members":{"targetElm":[{"__symbolic":"property","decorators":[{"__symbolic":"call","expression":{"__symbolic":"reference","module":"@angular/core","name":"Input"},"arguments":["xngClipboard"]}]}],"cbContent":[{"__symbolic":"property","decorators":[{"__symbolic":"call","expression":{"__symbolic":"reference","module":"@angular/core","name":"Input"}}]}],"onSuccess":[{"__symbolic":"property","decorators":[{"__symbolic":"call","expression":{"__symbolic":"reference","module":"@angular/core","name":"Output"},"arguments":["cbOnSuccess"]}]}],"onError":[{"__symbolic":"property","decorators":[{"__symbolic":"call","expression":{"__symbolic":"reference","module":"@angular/core","name":"Output"},"arguments":["cbOnError"]}]}],"__ctor__":[{"__symbolic":"constructor","parameters":[{"__symbolic":"reference","module":"@angular/core","name":"ElementRef"}]}],"ngOnInit":[{"__symbolic":"method"}],"ngOnDestroy":[{"__symbolic":"method"}]}}}}]